ui/__init__.py
ui/ui.py
uistyle-0.8.9.dist-info/METADATA
uistyle-0.8.9.dist-info/WHEEL
uistyle-0.8.9.dist-info/top_level.txt
uistyle-0.8.9.dist-info/RECORD
