Metadata-Version: 2.1
Name: uistyle
Version: 0.8.9
Summary: A beautiful console UI system For discord
Home-page: https://github.com/vivekxd669/myconsoleui
Author: ravan
Author-email: ravanxl@example.com
License: MIT
Classifier: Programming Language :: Python :: 3
Classifier: License :: OSI Approved :: MIT License
Classifier: Operating System :: OS Independent
Requires-Python: >=3.6
Requires-Dist: colorama
Requires-Dist: loguru
Requires-Dist: pyfiglet
Requires-Dist: rich
